__init__.py
qsensoropt/__init__.py
qsensoropt/bound_simulation.py
qsensoropt/circuits.py
qsensoropt/parameter.py
qsensoropt/particle_filter.py
qsensoropt/physical_model.py
qsensoropt/plot_utils.py
qsensoropt/schedulers.py
qsensoropt/simulation.py
qsensoropt/simulation_parameters.py
qsensoropt/stateful_metrology.py
qsensoropt/stateful_phys_model.py
qsensoropt/stateful_simulation.py
qsensoropt/stateless_metrology.py
qsensoropt/stateless_phys_model.py
qsensoropt/stateless_simulation.py
qsensoropt/utils.py
qsensoropt-1.0.0.dist-info/LICENSE
qsensoropt-1.0.0.dist-info/METADATA
qsensoropt-1.0.0.dist-info/WHEEL
qsensoropt-1.0.0.dist-info/top_level.txt
qsensoropt-1.0.0.dist-info/RECORD
