Metadata-Version: 2.1
Name: qsensoropt
Version: 1.0.0
Summary: https://arxiv.org/abs/2312.16985
Author-email: Federico Belliardo <federico.belliardo@sns.it>, Fabio Zoratti <fabio.zoratti@sns.it>
License: Apache License
Project-URL: Homepage, https://gitlab.com/federico.belliardo/qsensoropt
Project-URL: Bug Tracker, https://gitlab.com/federico.belliardo/qsensoropt/-/issues
Project-URL: Documentation, https://federico.belliardo.gitlab.io/qsensoropt/
Classifier: Programming Language :: Python :: 3 :: Only
Classifier: License :: OSI Approved :: Apache Software License
Classifier: Operating System :: OS Independent
Classifier: Development Status :: 3 - Alpha
Classifier: Topic :: Scientific/Engineering :: Physics
Classifier: Topic :: Scientific/Engineering :: Artificial Intelligence
Requires-Python: >=3.10
License-File: LICENSE
Requires-Dist: tensorflow <=2.12,>=2.6
Requires-Dist: numpy ~=1.19
Requires-Dist: pandas ~=1.5
Requires-Dist: progressbar2 ~=4.2.0
Requires-Dist: jupyter ~=1.0.0
Requires-Dist: matplotlib ~=3.7.1
Provides-Extra: docs
Requires-Dist: Sphinx ~=5.3.0 ; extra == 'docs'
Requires-Dist: sphinx-pyproject ~=0.1.0 ; extra == 'docs'
Requires-Dist: sphinx-rtd-theme ~=1.0.0 ; extra == 'docs'
Provides-Extra: lint
Requires-Dist: mypy ~=0.982 ; extra == 'lint'
Requires-Dist: pylint ~=2.15 ; extra == 'lint'
Requires-Dist: prospector ~=1.7 ; extra == 'lint'
Provides-Extra: tests
Requires-Dist: coverage ~=6.5.0 ; extra == 'tests'
